dynatrace/opentelemetry/gcf/__init__.py
dynatrace/opentelemetry/gcf/_resource.py
dynatrace/opentelemetry/gcf/_trigger.py
dynatrace/opentelemetry/gcf/_wrapper.py
dynatrace/opentelemetry/gcf/py.typed
dynatrace/opentelemetry/gcf/version.py
dynatrace_opentelemetry_gcf-1.329.2.dist-info/METADATA
dynatrace_opentelemetry_gcf-1.329.2.dist-info/WHEEL
dynatrace_opentelemetry_gcf-1.329.2.dist-info/licenses/LICENSE
dynatrace_opentelemetry_gcf-1.329.2.dist-info/RECORD
