Metadata-Version: 2.4
Name: dynatrace-opentelemetry-gcf
Version: 1.329.2
Summary: Dynatrace OpenTelemetry package for Google Cloud Functions
Project-URL: Homepage, https://www.dynatrace.com/technologies/python-monitoring/
Author: Dynatrace
License-Expression: Apache-2.0
License-File: LICENSE
Classifier: Development Status :: 5 - Production/Stable
Classifier: Intended Audience :: Developers
Classifier: License :: OSI Approved :: Apache Software License
Classifier: Programming Language :: Python
Classifier: Programming Language :: Python :: 3
Classifier: Programming Language :: Python :: 3.7
Classifier: Programming Language :: Python :: 3.8
Classifier: Programming Language :: Python :: 3.9
Classifier: Programming Language :: Python :: 3.10
Classifier: Programming Language :: Python :: 3.11
Classifier: Programming Language :: Python :: 3.12
Classifier: Programming Language :: Python :: 3.13
Classifier: Typing :: Typed
Requires-Python: >=3.7
Requires-Dist: dynatrace-opentelemetry-core==1.329.2
Requires-Dist: flask<4,>=1.0
Requires-Dist: opentelemetry-api~=1.3
Provides-Extra: test
